pyccel/__init__.py
pyccel/decorators.py
pyccel/version.py
pyccel/ast/__init__.py
pyccel/ast/basic.py
pyccel/ast/bind_c.py
pyccel/ast/bitwise_operators.py
pyccel/ast/builtin_imports.py
pyccel/ast/builtins.py
pyccel/ast/c_concepts.py
pyccel/ast/class_defs.py
pyccel/ast/cmathext.py
pyccel/ast/core.py
pyccel/ast/cwrapper.py
pyccel/ast/datatypes.py
pyccel/ast/fortran_concepts.py
pyccel/ast/functionalexpr.py
pyccel/ast/headers.py
pyccel/ast/internals.py
pyccel/ast/itertoolsext.py
pyccel/ast/literals.py
pyccel/ast/low_level_tools.py
pyccel/ast/mathext.py
pyccel/ast/numpy_wrapper.py
pyccel/ast/numpyext.py
pyccel/ast/numpytypes.py
pyccel/ast/omp.py
pyccel/ast/operators.py
pyccel/ast/scipyext.py
pyccel/ast/sympy_helper.py
pyccel/ast/sysext.py
pyccel/ast/type_annotations.py
pyccel/ast/typingext.py
pyccel/ast/utilities.py
pyccel/ast/variable.py
pyccel/ast/builtin_methods/dict_methods.py
pyccel/ast/builtin_methods/list_methods.py
pyccel/ast/builtin_methods/set_methods.py
pyccel/codegen/__init__.py
pyccel/codegen/codegen.py
pyccel/codegen/pipeline.py
pyccel/codegen/python_wrapper.py
pyccel/codegen/utilities.py
pyccel/codegen/compiling/__init__.py
pyccel/codegen/compiling/basic.py
pyccel/codegen/compiling/compilers.py
pyccel/codegen/compiling/file_locks.py
pyccel/codegen/printing/__init__.py
pyccel/codegen/printing/ccode.py
pyccel/codegen/printing/codeprinter.py
pyccel/codegen/printing/cwrappercode.py
pyccel/codegen/printing/fcode.py
pyccel/codegen/printing/pycode.py
pyccel/codegen/wrapper/__init__.py
pyccel/codegen/wrapper/c_to_python_wrapper.py
pyccel/codegen/wrapper/fortran_to_c_wrapper.py
pyccel/codegen/wrapper/wrapper.py
pyccel/commands/__init__.py
pyccel/commands/console.py
pyccel/commands/epyccel.py
pyccel/commands/lambdify.py
pyccel/commands/pyccel_clean.py
pyccel/commands/pyccel_test.py
pyccel/compilers/__init__.py
pyccel/compilers/default_compilers.py
pyccel/complexity/__init__.py
pyccel/complexity/arithmetic.py
pyccel/complexity/basic.py
pyccel/complexity/memory.py
pyccel-2.0.1.dist-info/METADATA
pyccel-2.0.1.dist-info/WHEEL
pyccel-2.0.1.dist-info/entry_points.txt
pyccel-2.0.1.dist-info/licenses/LICENSE
pyccel-2.0.1.dist-info/RECORD
