Metadata-Version: 2.4
Name: pyccel
Version: 2.0.1
Project-URL: Homepage, https://github.com/pyccel/pyccel
Project-URL: Documentation, https://pyccel.github.io/pyccel/
Project-URL: Source, https://github.com/pyccel/pyccel
Project-URL: Tracker, https://github.com/pyccel/pyccel/issues
Project-URL: Changelog, https://github.com/pyccel/pyccel/blob/devel/CHANGELOG.md
Author: Pyccel development team
License-Expression: MIT
License-File: LICENSE
Keywords: math
Requires-Python: >=3.9
Requires-Dist: filelock>=3.4.0
Requires-Dist: numpy!=2.0.*,>=1.16
Requires-Dist: packaging
Requires-Dist: sympy>=1.2
Requires-Dist: termcolor>=1.0.0
Requires-Dist: textx>=2.2
Provides-Extra: test
Requires-Dist: coverage>=3.1; extra == 'test'
Requires-Dist: mpi4py>=3.0.0; extra == 'test'
Requires-Dist: numpydoc>=1.8.0; extra == 'test'
Requires-Dist: pytest-mpi; extra == 'test'
Requires-Dist: pytest-xdist>=1.16; extra == 'test'
Requires-Dist: pytest>=7.0; extra == 'test'
Requires-Dist: scipy>=1.5.0; extra == 'test'
Requires-Dist: tblib>=1.7.0; extra == 'test'
